cosmotech/csm_orc/__init__.py
cosmotech/csm_orc/entrypoint.py
cosmotech/csm_orc/list_templates.py
cosmotech/csm_orc/main.py
cosmotech/csm_orc/run.py
cosmotech/orchestrator/__init__.py
cosmotech/orchestrator/api/__init__.py
cosmotech/orchestrator/api/entrypoint.py
cosmotech/orchestrator/api/run.py
cosmotech/orchestrator/api/templates.py
cosmotech/orchestrator/core/__init__.py
cosmotech/orchestrator/core/command_template.py
cosmotech/orchestrator/core/environment.py
cosmotech/orchestrator/core/orchestrator.py
cosmotech/orchestrator/core/runner.py
cosmotech/orchestrator/core/step.py
cosmotech/orchestrator/schema/run_template_json_schema.json
cosmotech/orchestrator/templates/__init__.py
cosmotech/orchestrator/templates/library.py
cosmotech/orchestrator/templates/plugin.py
cosmotech/orchestrator/utils/__init__.py
cosmotech/orchestrator/utils/click.py
cosmotech/orchestrator/utils/decorators.py
cosmotech/orchestrator/utils/json.py
cosmotech/orchestrator/utils/logger.py
cosmotech/orchestrator/utils/singleton.py
cosmotech/orchestrator/utils/translate.py
cosmotech/orchestrator_plugins/csm-orc/__init__.py
cosmotech/orchestrator_plugins/csm-orc/templates/.gitkeep
cosmotech/translation/csm-orc/__init__.py
cosmotech/translation/csm-orc/en-US/csm-orc/cli/entrypoint.yml
cosmotech/translation/csm-orc/en-US/csm-orc/cli/run.yml
cosmotech/translation/csm-orc/en-US/csm-orc/cli/templates.yml
cosmotech/translation/csm-orc/en-US/csm-orc/orchestrator/docs.yml
cosmotech/translation/csm-orc/en-US/csm-orc/orchestrator/errors.yml
cosmotech/translation/csm-orc/en-US/csm-orc/orchestrator/library.yml
cosmotech/translation/csm-orc/en-US/csm-orc/orchestrator/core/orchestrator.yml
cosmotech/translation/csm-orc/en-US/csm-orc/orchestrator/core/step.yml
cosmotech_run_orchestrator-2.0.2.dist-info/licenses/LICENSE
cosmotech_run_orchestrator-2.0.2.dist-info/METADATA
cosmotech_run_orchestrator-2.0.2.dist-info/WHEEL
cosmotech_run_orchestrator-2.0.2.dist-info/entry_points.txt
cosmotech_run_orchestrator-2.0.2.dist-info/top_level.txt
cosmotech_run_orchestrator-2.0.2.dist-info/RECORD
