Metadata-Version: 2.4
Name: cosmotech-run-orchestrator
Version: 2.0.2
Summary: Orchestration suite for Cosmotech Run Templates
Author-email: Cosmo Tech <platform@cosmotech.com>
Project-URL: Homepage, https://www.cosmotech.com
Project-URL: Source, https://github.com/Cosmo-Tech/run-orchestrator
Project-URL: Documentation, https://cosmo-tech.github.io/run-orchestrator/
License-File: LICENSE
Requires-Dist: flowpipe==1.0.0
Requires-Dist: jsonschema==4.21.1
Requires-Dist: pyyaml==6.0.1
Requires-Dist: python-logging-loki~=0.3.1
Requires-Dist: i18nice[YAML]
Requires-Dist: click==8.1.7
Requires-Dist: rich-click==1.7.3
Requires-Dist: click-log==0.4.0
Requires-Dist: rich==13.7.0
Provides-Extra: doc
Requires-Dist: mkdocs~=1.6.1; extra == "doc"
Requires-Dist: mkdocs-gen-files~=0.5.0; extra == "doc"
Requires-Dist: mkdocs-include-dir-to-nav~=1.2.0; extra == "doc"
Requires-Dist: mkdocs-literate-nav~=0.6.2; extra == "doc"
Requires-Dist: mkdocs-material[imaging]~=9.6.10; extra == "doc"
Requires-Dist: mkdocstrings[python]~=0.29.0; extra == "doc"
Requires-Dist: mike~=2.0.0; extra == "doc"
Requires-Dist: pymdown-extensions~=10.7; extra == "doc"
Requires-Dist: requirements-parser~=0.11.0; extra == "doc"
Provides-Extra: test
Requires-Dist: pytest~=8.0.0; extra == "test"
Requires-Dist: pytest-cov~=4.1.0; extra == "test"
Requires-Dist: pytest-mock~=3.12.0; extra == "test"
Requires-Dist: coverage~=7.4.0; extra == "test"
Provides-Extra: dev
Requires-Dist: black~=24.3.0; extra == "dev"
Requires-Dist: pre-commit~=3.6.0; extra == "dev"
Requires-Dist: flake8~=7.0.0; extra == "dev"
Requires-Dist: mypy~=1.8.0; extra == "dev"
Requires-Dist: isort~=5.13.0; extra == "dev"
Provides-Extra: extra
Provides-Extra: all
Requires-Dist: cosmotech-run-orchestrator[dev,doc,extra,test]; extra == "all"
Dynamic: license-file
